snugbug/__init__.py
snugbug/module.py
snugbug-0.0.dist-info/METADATA
snugbug-0.0.dist-info/WHEEL
snugbug-0.0.dist-info/top_level.txt
snugbug-0.0.dist-info/RECORD
