Metadata-Version: 2.1
Name: snugbug
Version: 0.0
Requires-Dist: socketio-client ==1.1.0
Requires-Dist: datetime
Requires-Dist: requests
